nrel/__init__.py
nrel/hive/__init__.py
nrel/hive/__main__.py
nrel/hive/py.typed
nrel/hive/app/__init__.py
nrel/hive/app/hive_cosim.py
nrel/hive/app/run.py
nrel/hive/app/run_batch.py
nrel/hive/config/__init__.py
nrel/hive/config/config_builder.py
nrel/hive/config/dispatcher_config.py
nrel/hive/config/global_config.py
nrel/hive/config/hive_config.py
nrel/hive/config/input.py
nrel/hive/config/network.py
nrel/hive/config/sim.py
nrel/hive/dispatcher/__init__.py
nrel/hive/dispatcher/forecaster/__init__.py
nrel/hive/dispatcher/forecaster/basic_forecaster.py
nrel/hive/dispatcher/forecaster/forecast.py
nrel/hive/dispatcher/forecaster/forecaster_interface.py
nrel/hive/dispatcher/instruction/__init__.py
nrel/hive/dispatcher/instruction/instruction.py
nrel/hive/dispatcher/instruction/instruction_ops.py
nrel/hive/dispatcher/instruction/instruction_result.py
nrel/hive/dispatcher/instruction/instructions.py
nrel/hive/dispatcher/instruction_generator/__init__.py
nrel/hive/dispatcher/instruction_generator/assignment_ops.py
nrel/hive/dispatcher/instruction_generator/charging_fleet_manager.py
nrel/hive/dispatcher/instruction_generator/charging_search_type.py
nrel/hive/dispatcher/instruction_generator/dispatcher.py
nrel/hive/dispatcher/instruction_generator/instruction_function.py
nrel/hive/dispatcher/instruction_generator/instruction_generator.py
nrel/hive/dispatcher/instruction_generator/instruction_generator_ops.py
nrel/hive/initialization/__init__.py
nrel/hive/initialization/initialize_ops.py
nrel/hive/initialization/initialize_simulation.py
nrel/hive/initialization/initialize_simulation_with_sampling.py
nrel/hive/initialization/load.py
nrel/hive/initialization/sample_requests.py
nrel/hive/initialization/sample_vehicles.py
nrel/hive/model/__init__.py
nrel/hive/model/base.py
nrel/hive/model/entity.py
nrel/hive/model/entity_position.py
nrel/hive/model/membership.py
nrel/hive/model/passenger.py
nrel/hive/model/sim_time.py
nrel/hive/model/energy/__init__.py
nrel.hive-1.3.1.dist-info/LICENSE
nrel.hive-1.3.1.dist-info/METADATA
nrel.hive-1.3.1.dist-info/WHEEL
nrel.hive-1.3.1.dist-info/entry_points.txt
nrel.hive-1.3.1.dist-info/top_level.txt
nrel.hive-1.3.1.dist-info/RECORD
