Metadata-Version: 2.1
Name: nrel.hive
Version: 1.3.1
Summary: HIVE is a mobility services research platform developed by the Mobility and Advanced Powertrains (MBAP) group at the National Renewable Energy Laboratory in Golden, Colorado, USA.
Author: National Renewable Energy Laboratory
License: BSD 3-Clause License Copyright (c) 2022, Alliance for Sustainable Energy, LLC
Project-URL: Homepage, https://github.com/NREL/hive
Keywords: simulation,transportation,ride-sharing,agent-based
Classifier: Development Status :: 3 - Alpha
Classifier: Intended Audience :: Science/Research
Classifier: License :: Other/Proprietary License
Classifier: Operating System :: OS Independent
Classifier: Programming Language :: Python
Classifier: Programming Language :: Python :: 3.8
Classifier: Topic :: Scientific/Engineering
Requires-Python: >=3.8
License-File: LICENSE
Requires-Dist: immutables
Requires-Dist: numpy
Requires-Dist: networkx
Requires-Dist: PyYAML
Requires-Dist: tqdm
Requires-Dist: rich
Requires-Dist: h3 (<4)
Requires-Dist: scipy
Requires-Dist: returns
Provides-Extra: dev
Requires-Dist: nrel.hive[docs] ; extra == 'dev'
Requires-Dist: pytest ; extra == 'dev'
Requires-Dist: black (==23.1.0) ; extra == 'dev'
Requires-Dist: mypy ; extra == 'dev'
Requires-Dist: twine ; extra == 'dev'
Requires-Dist: types-PyYAML ; extra == 'dev'
Requires-Dist: types-setuptools ; extra == 'dev'
Requires-Dist: pre-commit ; extra == 'dev'
Provides-Extra: docs
Requires-Dist: sphinx (<7) ; extra == 'docs'
Requires-Dist: sphinx-autoapi ; extra == 'docs'
Requires-Dist: sphinx-rtd-theme ; extra == 'docs'
Requires-Dist: sphinxemoji ; extra == 'docs'
Requires-Dist: myst-parser ; extra == 'docs'
Requires-Dist: sphinx-autodoc-typehints ; extra == 'docs'
